ConTEST/CONTEST.py
ConTEST/__init__.py
ConsistencyTEST-0.0.2.dist-info/LICENSE
ConsistencyTEST-0.0.2.dist-info/METADATA
ConsistencyTEST-0.0.2.dist-info/WHEEL
ConsistencyTEST-0.0.2.dist-info/top_level.txt
ConsistencyTEST-0.0.2.dist-info/RECORD
