Metadata-Version: 2.1
Name: ConsistencyTEST
Version: 0.0.2
Summary: Consistency test
Home-page: https://github.com/FiorenST/ConTEST
Author: Fiorenzo Stoppa
Author-email: f.stoppa@astro.ru.nl
Project-URL: Bug Tracker, https://github.com/FiorenST/ConTEST/issues
Classifier: Programming Language :: Python :: 3
Classifier: License :: OSI Approved :: Apache Software License
Classifier: Operating System :: OS Independent
Requires-Python: >=3.6
License-File: LICENSE
